<?xml version="1.0" encoding="utf-8"?><api:response xmlns:api="http://www.symplectic.co.uk/publications/api"><api:version uri="https://mypublications.shef.ac.uk/" elements-version="6.17.0.4095" schema-version="6.13" product-name="myPublications"/><api:request href="https://mypublications.shef.ac.uk:8091/secure-api/v6.13/activities/1348440"/><api:result><api:object category="activity" id="1348440" last-affected-when="2024-03-07T06:00:15.433+00:00" last-modified-when="2021-03-10T09:54:38.88+00:00" href="https://mypublications.shef.ac.uk:8091/secure-api/v6.13/activities/1348440" created-when="2021-03-10T09:54:37.513+00:00" type-id="57" type-display-name="Reviewing / refereeing for a publisher" type="c-publisher-reviewing"><api:privacy-level>Public</api:privacy-level><api:privacy-level-locked>false</api:privacy-level-locked><api:ever-approved>true</api:ever-approved><api:reporting-date-1>2021-01-02</api:reporting-date-1><api:allow-type-switching>true</api:allow-type-switching><api:records><api:record format="native" id="3660111" source-id="1" source-name="manual" source-display-name="Manual" id-at-source="2A17EDB5-D418-4BAD-A5E5-4BB9A03AF416" last-modified-when="2021-03-10T09:54:37.543+00:00"><api:verification-status>unverified</api:verification-status><api:native><api:field name="amount" type="integer" display-name="No. works reviewed / refereed during period"><api:integer>1</api:integer></api:field><api:field name="c-invite-refused" type="boolean" display-name="Invite declined"><api:boolean>false</api:boolean></api:field><api:field name="c-publisher" type="text" display-name="Publisher"><api:text>Evolving Systems</api:text></api:field><api:field name="end-date" type="date" display-name="End date"><api:date><api:day>6</api:day><api:month>2</api:month><api:year>2021</api:year></api:date></api:field><api:field name="review-type" type="text" display-name="Review type"><api:text>Anonymous peer review</api:text></api:field><api:field name="start-date" type="date" display-name="Start date"><api:date><api:day>2</api:day><api:month>1</api:month><api:year>2021</api:year></api:date></api:field></api:native></api:record></api:records><api:fields/><api:relationships href="https://mypublications.shef.ac.uk:8091/secure-api/v6.13/activities/1348440/relationships"/></api:object></api:result></api:response>