<?xml version="1.0" encoding="utf-8"?><api:response xmlns:api="http://www.symplectic.co.uk/publications/api"><api:version uri="https://mypublications.shef.ac.uk/" elements-version="6.17.0.4095" schema-version="6.13" product-name="myPublications"/><api:request href="https://mypublications.shef.ac.uk:8091/secure-api/v6.13/publications/57571"/><api:result><api:object category="publication" id="57571" last-affected-when="2024-05-07T18:04:04.43+01:00" last-modified-when="2024-05-07T18:04:04.43+01:00" href="https://mypublications.shef.ac.uk:8091/secure-api/v6.13/publications/57571" created-when="2010-06-19T12:33:54.267+01:00" type-id="5" type-display-name="Journal article" type="journal-article"><api:privacy-level>Public</api:privacy-level><api:privacy-level-locked>false</api:privacy-level-locked><api:ever-approved>true</api:ever-approved><api:reporting-date-1>2010-05-27</api:reporting-date-1><api:allow-type-switching>true</api:allow-type-switching><api:records><api:record format="native" id="1400840" source-id="13" source-name="crossref" source-display-name="Crossref" id-at-source="10.1016/j.pbiomolbio.2010.05.008" last-modified-when="2022-09-10T12:46:35.793+01:00"><api:native><api:field name="authors" type="person-list" display-name="Authors"><api:people><api:person><api:links><api:link type="elements/user" id="310" href="https://mypublications.shef.ac.uk:8091/secure-api/v6.13/users/310"/></api:links><api:last-name>Clayton</api:last-name><api:initials>RH</api:initials><api:first-names>RH</api:first-names><api:separate-first-names><api:first-name>R</api:first-name><api:first-name>H</api:first-name></api:separate-first-names></api:person><api:person><api:last-name>Bernus</api:last-name><api:initials>O</api:initials><api:first-names>O</api:first-names><api:separate-first-names><api:first-name>O</api:first-name></api:separate-first-names></api:person><api:person><api:last-name>Cherry</api:last-name><api:initials>EM</api:initials><api:first-names>EM</api:first-names><api:separate-first-names><api:first-name>E</api:first-name><api:first-name>M</api:first-name></api:separate-first-names></api:person><api:person><api:last-name>Dierckx</api:last-name><api:initials>H</api:initials><api:first-names>H</api:first-names><api:separate-first-names><api:first-name>H</api:first-name></api:separate-first-names></api:person><api:person><api:last-name>Fenton</api:last-name><api:initials>FH</api:initials><api:first-names>FH</api:first-names><api:separate-first-names><api:first-name>F</api:first-name><api:first-name>H</api:first-name></api:separate-first-names></api:person><api:person><api:last-name>Mirabella</api:last-name><api:initials>L</api:initials><api:first-names>L</api:first-names><api:separate-first-names><api:first-name>L</api:first-name></api:separate-first-names></api:person><api:person><api:last-name>Panfilov</api:last-name><api:initials>AV</api:initials><api:first-names>AV</api:first-names><api:separate-first-names><api:first-name>A</api:first-name><api:first-name>V</api:first-name></api:separate-first-names></api:person><api:person><api:last-name>Sachse</api:last-name><api:initials>FB</api:initials><api:first-names>FB</api:first-names><api:separate-first-names><api:first-name>F</api:first-name><api:first-name>B</api:first-name></api:separate-first-names></api:person><api:person><api:last-name>Seemann</api:last-name><api:initials>G</api:initials><api:first-names>G</api:first-names><api:separate-first-names><api:first-name>G</api:first-name></api:separate-first-names></api:person><api:person><api:last-name>Zhang</api:last-name><api:initials>H</api:initials><api:first-names>H</api:first-names><api:separate-first-names><api:first-name>H</api:first-name></api:separate-first-names></api:person></api:people></api:field><api:field name="doi" type="text" display-name="DOI"><api:text>10.1016/j.pbiomolbio.2010.05.008</api:text><api:links><api:link type="doi" href="http://doi.org/10.1016/j.pbiomolbio.2010.05.008"/><api:link type="altmetric" href="http://www.altmetric.com/details.php?doi=10.1016/j.pbiomolbio.2010.05.008"/></api:links></api:field><api:field name="issn" type="text" display-name="ISSN"><api:text>0079-6107</api:text><api:links><api:link type="elements/journal" href="https://mypublications.shef.ac.uk:8091/secure-api/v6.13/journals/965661"/></api:links></api:field><api:field name="issue" type="text" display-name="Issue"><api:text>1-3</api:text></api:field><api:field name="journal" type="text" display-name="Journal"><api:text>Progress in Biophysics and Molecular Biology</api:text></api:field><api:field name="language" type="text" display-name="Language"><api:text>en</api:text></api:field><api:field name="pagination" type="pagination" display-name="Pagination"><api:pagination><api:begin-page>22</api:begin-page><api:end-page>48</api:end-page></api:pagination></api:field><api:field name="publication-date" type="date" display-name="Publication date"><api:date><api:month>1</api:month><api:year>2011</api:year></api:date></api:field><api:field name="publication-status" type="text" display-name="Status"><api:text>Published</api:text></api:field><api:field name="publisher" type="text" display-name="Publisher"><api:text>Elsevier BV</api:text></api:field><api:field name="publisher-url" type="text" display-name="Link 2"><api:text>http://dx.doi.org/10.1016/j.pbiomolbio.2010.05.008</api:text></api:field><api:field name="record-created-at-source-date" type="date" display-name="Record created at source"><api:date><api:day>29</api:day><api:month>5</api:month><api:year>2019</api:year></api:date></api:field><api:field name="title" type="text" display-name="Title"><api:text>Models of cardiac tissue electrophysiology: Progress, challenges and open questions</api:text></api:field><api:field name="volume" type="text" display-name="Volume"><api:text>104</api:text></api:field></api:native></api:record><api:record format="native" id="153733" source-id="7" source-name="scopus" source-display-name="Scopus" id-at-source="2-s2.0-78650868377" last-modified-when="2024-05-07T18:04:04.44+01:00"><api:citation-count>451</api:citation-count><api:native><api:field name="abstract" type="text" display-name="Abstract"><api:text>Models of cardiac tissue electrophysiology are an important component of the Cardiac Physiome Project, which is an international effort to build biophysically based multi-scale mathematical models of the heart. Models of tissue electrophysiology can provide a bridge between electrophysiological cell models at smaller scales, and tissue mechanics, metabolism and blood flow at larger scales. This paper is a critical review of cardiac tissue electrophysiology models, focussing on the micro-structure of cardiac tissue, generic behaviours of action potential propagation, different models of cardiac tissue electrophysiology, the choice of parameter values and tissue geometry, emergent properties in tissue models, numerical techniques and computational issues. We propose a tentative list of information that could be included in published descriptions of tissue electrophysiology models, and used to support interpretation and evaluation of simulation results. We conclude with a discussion of challenges and open questions. © 2010 Elsevier Ltd.</api:text></api:field><api:field name="authors" type="person-list" display-name="Authors"><api:people><api:person><api:links><api:link type="elements/user" id="310" href="https://mypublications.shef.ac.uk:8091/secure-api/v6.13/users/310"/></api:links><api:last-name>Clayton</api:last-name><api:initials>RH</api:initials><api:first-names>RH</api:first-names><api:separate-first-names><api:first-name>R</api:first-name><api:first-name>H</api:first-name></api:separate-first-names><api:addresses><api:address iso-country-code="GB"><api:line type="organisation">The University of Sheffield</api:line><api:line type="city">Sheffield</api:line><api:line type="country">United Kingdom</api:line></api:address></api:addresses><api:identifiers><api:identifier scheme="scopus-author-id">56243052600</api:identifier></api:identifiers></api:person><api:person><api:last-name>Bernus</api:last-name><api:initials>O</api:initials><api:first-names>O</api:first-names><api:separate-first-names><api:first-name>O</api:first-name></api:separate-first-names><api:addresses><api:address iso-country-code="GB"><api:line type="organisation">University of Leeds</api:line><api:line type="city">Leeds</api:line><api:line type="country">United Kingdom</api:line></api:address></api:addresses><api:identifiers><api:identifier scheme="scopus-author-id">6603188890</api:identifier></api:identifiers></api:person><api:person><api:last-name>Cherry</api:last-name><api:initials>EM</api:initials><api:first-names>EM</api:first-names><api:separate-first-names><api:first-name>E</api:first-name><api:first-name>M</api:first-name></api:separate-first-names><api:addresses><api:address iso-country-code="US"><api:line type="organisation">Cornell University</api:line><api:line type="city">Ithaca</api:line><api:line type="country">United States</api:line></api:address></api:addresses><api:identifiers><api:identifier scheme="scopus-author-id">7004218125</api:identifier></api:identifiers></api:person><api:person><api:last-name>Dierckx</api:last-name><api:initials>H</api:initials><api:first-names>H</api:first-names><api:separate-first-names><api:first-name>H</api:first-name></api:separate-first-names><api:addresses><api:address iso-country-code="BE"><api:line type="organisation">Universiteit Gent</api:line><api:line type="city">Ghent</api:line><api:line type="country">Belgium</api:line></api:address></api:addresses><api:identifiers><api:identifier scheme="scopus-author-id">23008283600</api:identifier></api:identifiers></api:person><api:person><api:last-name>Fenton</api:last-name><api:initials>FH</api:initials><api:first-names>FH</api:first-names><api:separate-first-names><api:first-name>F</api:first-name><api:first-name>H</api:first-name></api:separate-first-names><api:addresses><api:address iso-country-code="US"><api:line type="organisation">Cornell University</api:line><api:line type="city">Ithaca</api:line><api:line type="country">United States</api:line></api:address></api:addresses><api:identifiers><api:identifier scheme="scopus-author-id">7003983519</api:identifier></api:identifiers></api:person><api:person><api:last-name>Mirabella</api:last-name><api:initials>L</api:initials><api:first-names>L</api:first-names><api:separate-first-names><api:first-name>L</api:first-name></api:separate-first-names><api:addresses><api:address iso-country-code="US"><api:line type="organisation">Emory University</api:line><api:line type="city">Atlanta</api:line><api:line type="country">United States</api:line></api:address><api:address iso-country-code="IT"><api:line type="organisation">Politecnico di Milano</api:line><api:line type="city">Milan</api:line><api:line type="country">Italy</api:line></api:address></api:addresses><api:identifiers><api:identifier scheme="scopus-author-id">16230821300</api:identifier></api:identifiers></api:person><api:person><api:last-name>Panfilov</api:last-name><api:initials>AV</api:initials><api:first-names>AV</api:first-names><api:separate-first-names><api:first-name>A</api:first-name><api:first-name>V</api:first-name></api:separate-first-names><api:addresses><api:address iso-country-code="NL"><api:line type="organisation">Universiteit Utrecht</api:line><api:line type="city">Utrecht</api:line><api:line type="country">Netherlands</api:line></api:address></api:addresses><api:identifiers><api:identifier scheme="scopus-author-id">35585363900</api:identifier></api:identifiers></api:person><api:person><api:last-name>Sachse</api:last-name><api:initials>FB</api:initials><api:first-names>FB</api:first-names><api:separate-first-names><api:first-name>F</api:first-name><api:first-name>B</api:first-name></api:separate-first-names><api:addresses><api:address iso-country-code="US"><api:line type="organisation">University of Utah School of Medicine</api:line><api:line type="city">Salt Lake City</api:line><api:line type="country">United States</api:line></api:address></api:addresses><api:identifiers><api:identifier scheme="scopus-author-id">7004225157</api:identifier></api:identifiers></api:person><api:person><api:last-name>Seemann</api:last-name><api:initials>G</api:initials><api:first-names>G</api:first-names><api:separate-first-names><api:first-name>G</api:first-name></api:separate-first-names><api:addresses><api:address iso-country-code="DE"><api:line type="organisation">Karlsruher Institut für Technologie</api:line><api:line type="city">Karlsruhe</api:line><api:line type="country">Germany</api:line></api:address></api:addresses><api:identifiers><api:identifier scheme="scopus-author-id">7004128584</api:identifier></api:identifiers></api:person><api:person><api:last-name>Zhang</api:last-name><api:initials>H</api:initials><api:first-names>H</api:first-names><api:separate-first-names><api:first-name>H</api:first-name></api:separate-first-names><api:addresses><api:address iso-country-code="GB"><api:line type="organisation">The University of Manchester</api:line><api:line type="city">Manchester</api:line><api:line type="country">United Kingdom</api:line></api:address></api:addresses><api:identifiers><api:identifier scheme="scopus-author-id">9532347100</api:identifier></api:identifiers></api:person></api:people></api:field><api:field name="doi" type="text" display-name="DOI"><api:text>10.1016/j.pbiomolbio.2010.05.008</api:text><api:links><api:link type="doi" href="http://doi.org/10.1016/j.pbiomolbio.2010.05.008"/><api:link type="altmetric" href="http://www.altmetric.com/details.php?doi=10.1016/j.pbiomolbio.2010.05.008"/></api:links></api:field><api:field name="external-identifiers" type="identifier-list" display-name="External identifiers"><api:identifiers><api:identifier scheme="pubmed">20553746</api:identifier></api:identifiers></api:field><api:field name="issn" type="text" display-name="ISSN"><api:text>0079-6107</api:text><api:links><api:link type="elements/journal" href="https://mypublications.shef.ac.uk:8091/secure-api/v6.13/journals/965661"/></api:links></api:field><api:field name="issue" type="text" display-name="Issue"><api:text>1-3</api:text></api:field><api:field name="journal" type="text" display-name="Journal"><api:text>Progress in Biophysics and Molecular Biology</api:text></api:field><api:field name="pagination" type="pagination" display-name="Pagination"><api:pagination><api:begin-page>22</api:begin-page><api:end-page>48</api:end-page></api:pagination></api:field><api:field name="publication-date" type="date" display-name="Publication date"><api:date><api:day>1</api:day><api:month>1</api:month><api:year>2011</api:year></api:date></api:field><api:field name="publication-status" type="text" display-name="Status"><api:text>Published</api:text></api:field><api:field name="title" type="text" display-name="Title"><api:text>Models of cardiac tissue electrophysiology: Progress, challenges and open questions</api:text></api:field><api:field name="types" type="list" display-name="Sub types"><api:items><api:item>Review</api:item></api:items></api:field><api:field name="volume" type="text" display-name="Volume"><api:text>104</api:text></api:field></api:native></api:record><api:record format="native" id="74380" source-id="2" source-name="pubmed" source-display-name="PubMed" id-at-source="20553746" last-modified-when="2020-04-29T13:51:58.807+01:00"><api:native><api:field name="abstract" type="text" display-name="Abstract"><api:text>Models of cardiac tissue electrophysiology are an important component of the Cardiac Physiome Project, which is an international effort to build biophysically based multi-scale mathematical models of the heart. Models of tissue electrophysiology can provide a bridge between electrophysiological cell models at smaller scales, and tissue mechanics, metabolism and blood flow at larger scales. This paper is a critical review of cardiac tissue electrophysiology models, focussing on the micro-structure of cardiac tissue, generic behaviours of action potential propagation, different models of cardiac tissue electrophysiology, the choice of parameter values and tissue geometry, emergent properties in tissue models, numerical techniques and computational issues. We propose a tentative list of information that could be included in published descriptions of tissue electrophysiology models, and used to support interpretation and evaluation of simulation results. We conclude with a discussion of challenges and open questions.</api:text></api:field><api:field name="acceptance-date" type="date" display-name="Date of acceptance"><api:date><api:day>19</api:day><api:month>5</api:month><api:year>2010</api:year></api:date></api:field><api:field name="authors" type="person-list" display-name="Authors"><api:people><api:person><api:links><api:link type="elements/user" id="310" href="https://mypublications.shef.ac.uk:8091/secure-api/v6.13/users/310"/></api:links><api:last-name>Clayton</api:last-name><api:initials>RH</api:initials><api:first-names>RH</api:first-names><api:separate-first-names><api:first-name>R</api:first-name><api:first-name>H</api:first-name></api:separate-first-names><api:addresses><api:address iso-country-code="GB"><api:line type="full">Department of Computer Science, University of Sheffield, Regent Court, 211 Portobello Street, Sheffield S1 4DP, UK. r.h.clayton@sheffield.ac.uk</api:line></api:address></api:addresses><api:email-address>r.h.clayton@sheffield.ac.uk</api:email-address></api:person><api:person><api:last-name>Bernus</api:last-name><api:initials>O</api:initials><api:first-names>O</api:first-names><api:separate-first-names><api:first-name>O</api:first-name></api:separate-first-names></api:person><api:person><api:last-name>Cherry</api:last-name><api:initials>EM</api:initials><api:first-names>EM</api:first-names><api:separate-first-names><api:first-name>E</api:first-name><api:first-name>M</api:first-name></api:separate-first-names></api:person><api:person><api:last-name>Dierckx</api:last-name><api:initials>H</api:initials><api:first-names>H</api:first-names><api:separate-first-names><api:first-name>H</api:first-name></api:separate-first-names></api:person><api:person><api:last-name>Fenton</api:last-name><api:initials>FH</api:initials><api:first-names>FH</api:first-names><api:separate-first-names><api:first-name>F</api:first-name><api:first-name>H</api:first-name></api:separate-first-names></api:person><api:person><api:last-name>Mirabella</api:last-name><api:initials>L</api:initials><api:first-names>L</api:first-names><api:separate-first-names><api:first-name>L</api:first-name></api:separate-first-names></api:person><api:person><api:last-name>Panfilov</api:last-name><api:initials>AV</api:initials><api:first-names>AV</api:first-names><api:separate-first-names><api:first-name>A</api:first-name><api:first-name>V</api:first-name></api:separate-first-names></api:person><api:person><api:last-name>Sachse</api:last-name><api:initials>FB</api:initials><api:first-names>FB</api:first-names><api:separate-first-names><api:first-name>F</api:first-name><api:first-name>B</api:first-name></api:separate-first-names></api:person><api:person><api:last-name>Seemann</api:last-name><api:initials>G</api:initials><api:first-names>G</api:first-names><api:separate-first-names><api:first-name>G</api:first-name></api:separate-first-names></api:person><api:person><api:last-name>Zhang</api:last-name><api:initials>H</api:initials><api:first-names>H</api:first-names><api:separate-first-names><api:first-name>H</api:first-name></api:separate-first-names></api:person></api:people></api:field><api:field name="author-url" type="text" display-name="Link 1"><api:text>https://www.ncbi.nlm.nih.gov/pubmed/20553746</api:text></api:field><api:field name="doi" type="text" display-name="DOI"><api:text>10.1016/j.pbiomolbio.2010.05.008</api:text><api:links><api:link type="doi" href="http://doi.org/10.1016/j.pbiomolbio.2010.05.008"/><api:link type="altmetric" href="http://www.altmetric.com/details.php?doi=10.1016/j.pbiomolbio.2010.05.008"/></api:links></api:field><api:field name="eissn" type="text" display-name="eISSN"><api:text>1873-1732</api:text><api:links><api:link type="elements/journal" href="https://mypublications.shef.ac.uk:8091/secure-api/v6.13/journals/965661"/></api:links></api:field><api:field name="issue" type="text" display-name="Issue"><api:text>1-3</api:text></api:field><api:field name="journal" type="text" display-name="Journal"><api:text>Prog Biophys Mol Biol</api:text></api:field><api:field name="keywords" type="keyword-list" display-name="Keywords"><api:keywords><api:keyword scheme="mesh">Action Potentials</api:keyword><api:keyword scheme="mesh">Animals</api:keyword><api:keyword scheme="mesh">Cardiac Electrophysiology</api:keyword><api:keyword scheme="mesh">Cell Physiological Phenomena</api:keyword><api:keyword scheme="mesh">Forecasting</api:keyword><api:keyword scheme="mesh">Heart</api:keyword><api:keyword scheme="mesh">Humans</api:keyword><api:keyword scheme="mesh">Models, Cardiovascular</api:keyword><api:keyword scheme="mesh">Myocardium</api:keyword><api:keyword scheme="mesh">Rabbits</api:keyword></api:keywords></api:field><api:field name="language" type="text" display-name="Language"><api:text>eng</api:text></api:field><api:field name="location" type="text" display-name="Country"><api:text>England</api:text></api:field><api:field name="pagination" type="pagination" display-name="Pagination"><api:pagination><api:begin-page>22</api:begin-page><api:end-page>48</api:end-page></api:pagination></api:field><api:field name="pii" type="text" display-name="PII"><api:text>S0079-6107(10)00036-2</api:text></api:field><api:field name="publication-date" type="date" display-name="Publication date"><api:date><api:month>1</api:month><api:year>2011</api:year></api:date></api:field><api:field name="publication-status" type="text" display-name="Status"><api:text>Published</api:text></api:field><api:field name="record-made-public-at-source-date" type="date" display-name="Record made publicly available"><api:date><api:day>1</api:day><api:month>4</api:month><api:year>2011</api:year></api:date></api:field><api:field name="title" type="text" display-name="Title"><api:text>Models of cardiac tissue electrophysiology: progress, challenges and open questions.</api:text></api:field><api:field name="types" type="list" display-name="Sub types"><api:items><api:item>Journal Article</api:item><api:item>Research Support, Non-U.S. Gov't</api:item><api:item>Research Support, U.S. Gov't, Non-P.H.S.</api:item><api:item>Review</api:item></api:items></api:field><api:field name="volume" type="text" display-name="Volume"><api:text>104</api:text></api:field></api:native></api:record><api:record format="native" id="894686" source-id="18" source-name="epmc" source-display-name="Europe PubMed Central" id-at-source="MED:20553746" last-modified-when="2024-03-26T20:08:04.103+00:00"><api:citation-count>217</api:citation-count><api:native><api:field name="abstract" type="text" display-name="Abstract"><api:text>Models of cardiac tissue electrophysiology are an important component of the Cardiac Physiome Project, which is an international effort to build biophysically based multi-scale mathematical models of the heart. Models of tissue electrophysiology can provide a bridge between electrophysiological cell models at smaller scales, and tissue mechanics, metabolism and blood flow at larger scales. This paper is a critical review of cardiac tissue electrophysiology models, focussing on the micro-structure of cardiac tissue, generic behaviours of action potential propagation, different models of cardiac tissue electrophysiology, the choice of parameter values and tissue geometry, emergent properties in tissue models, numerical techniques and computational issues. We propose a tentative list of information that could be included in published descriptions of tissue electrophysiology models, and used to support interpretation and evaluation of simulation results. We conclude with a discussion of challenges and open questions.</api:text></api:field><api:field name="addresses" type="address-list" display-name="Addresses"><api:addresses><api:address iso-country-code="GB"><api:line type="full">Department of Computer Science, University of Sheffield, Regent Court, 211 Portobello Street, Sheffield S1 4DP, UK. r.h.clayton@sheffield.ac.uk</api:line></api:address></api:addresses></api:field><api:field name="authors" type="person-list" display-name="Authors"><api:people><api:person><api:links><api:link type="elements/user" id="310" href="https://mypublications.shef.ac.uk:8091/secure-api/v6.13/users/310"/></api:links><api:last-name>Clayton</api:last-name><api:initials>RH</api:initials><api:first-names>RH</api:first-names><api:separate-first-names><api:first-name>R</api:first-name><api:first-name>H</api:first-name></api:separate-first-names><api:identifiers><api:identifier scheme="orcid">0000-0002-8438-7518</api:identifier></api:identifiers></api:person><api:person><api:last-name>Bernus</api:last-name><api:initials>O</api:initials><api:first-names>O</api:first-names><api:separate-first-names><api:first-name>O</api:first-name></api:separate-first-names><api:identifiers><api:identifier scheme="orcid">0000-0003-3917-5791</api:identifier></api:identifiers></api:person><api:person><api:last-name>Cherry</api:last-name><api:initials>EM</api:initials><api:first-names>EM</api:first-names><api:separate-first-names><api:first-name>E</api:first-name><api:first-name>M</api:first-name></api:separate-first-names><api:identifiers><api:identifier scheme="orcid">0000-0001-5194-9572</api:identifier></api:identifiers></api:person><api:person><api:last-name>Dierckx</api:last-name><api:initials>H</api:initials><api:first-names>H</api:first-names><api:separate-first-names><api:first-name>H</api:first-name></api:separate-first-names><api:identifiers><api:identifier scheme="orcid">0000-0003-0899-8082</api:identifier></api:identifiers></api:person><api:person><api:last-name>Fenton</api:last-name><api:initials>FH</api:initials><api:first-names>FH</api:first-names><api:separate-first-names><api:first-name>F</api:first-name><api:first-name>H</api:first-name></api:separate-first-names></api:person><api:person><api:last-name>Mirabella</api:last-name><api:initials>L</api:initials><api:first-names>L</api:first-names><api:separate-first-names><api:first-name>L</api:first-name></api:separate-first-names></api:person><api:person><api:last-name>Panfilov</api:last-name><api:initials>AV</api:initials><api:first-names>AV</api:first-names><api:separate-first-names><api:first-name>A</api:first-name><api:first-name>V</api:first-name></api:separate-first-names><api:identifiers><api:identifier scheme="orcid">0000-0003-2643-642X</api:identifier></api:identifiers></api:person><api:person><api:last-name>Sachse</api:last-name><api:initials>FB</api:initials><api:first-names>FB</api:first-names><api:separate-first-names><api:first-name>F</api:first-name><api:first-name>B</api:first-name></api:separate-first-names><api:identifiers><api:identifier scheme="orcid">0000-0003-4987-705X</api:identifier></api:identifiers></api:person><api:person><api:last-name>Seemann</api:last-name><api:initials>G</api:initials><api:first-names>G</api:first-names><api:separate-first-names><api:first-name>G</api:first-name></api:separate-first-names></api:person><api:person><api:last-name>Zhang</api:last-name><api:initials>H</api:initials><api:first-names>H</api:first-names><api:separate-first-names><api:first-name>H</api:first-name></api:separate-first-names></api:person></api:people></api:field><api:field name="doi" type="text" display-name="DOI"><api:text>10.1016/j.pbiomolbio.2010.05.008</api:text><api:links><api:link type="doi" href="http://doi.org/10.1016/j.pbiomolbio.2010.05.008"/><api:link type="altmetric" href="http://www.altmetric.com/details.php?doi=10.1016/j.pbiomolbio.2010.05.008"/></api:links></api:field><api:field name="eissn" type="text" display-name="eISSN"><api:text>1873-1732</api:text><api:links><api:link type="elements/journal" href="https://mypublications.shef.ac.uk:8091/secure-api/v6.13/journals/965661"/></api:links></api:field><api:field name="external-identifiers" type="identifier-list" display-name="External identifiers"><api:identifiers><api:identifier scheme="pubmed">20553746</api:identifier></api:identifiers></api:field><api:field name="is-open-access" type="boolean" display-name="Open access"><api:boolean>false</api:boolean></api:field><api:field name="issn" type="text" display-name="ISSN"><api:text>0079-6107</api:text><api:links><api:link type="elements/journal" href="https://mypublications.shef.ac.uk:8091/secure-api/v6.13/journals/965661"/></api:links></api:field><api:field name="issue" type="text" display-name="Issue"><api:text>1-3</api:text></api:field><api:field name="journal" type="text" display-name="Journal"><api:text>Progress in biophysics and molecular biology</api:text></api:field><api:field name="keywords" type="keyword-list" display-name="Keywords"><api:keywords><api:keyword scheme="mesh">Myocardium</api:keyword><api:keyword scheme="mesh">Heart</api:keyword><api:keyword scheme="mesh">Animals</api:keyword><api:keyword scheme="mesh">Rabbits</api:keyword><api:keyword scheme="mesh">Humans</api:keyword><api:keyword scheme="mesh">Action Potentials</api:keyword><api:keyword scheme="mesh">Models, Cardiovascular</api:keyword><api:keyword scheme="mesh">Forecasting</api:keyword><api:keyword scheme="mesh">Cardiac Electrophysiology</api:keyword><api:keyword scheme="mesh">Cell Physiological Phenomena</api:keyword></api:keywords></api:field><api:field name="language" type="text" display-name="Language"><api:text>eng</api:text></api:field><api:field name="medium" type="text" display-name="Medium"><api:text>Print-Electronic</api:text></api:field><api:field name="online-publication-date" type="date" display-name="Online publication date"><api:date><api:day>27</api:day><api:month>5</api:month><api:year>2010</api:year></api:date></api:field><api:field name="pagination" type="pagination" display-name="Pagination"><api:pagination><api:begin-page>22</api:begin-page><api:end-page>48</api:end-page></api:pagination></api:field><api:field name="publication-date" type="date" display-name="Publication date"><api:date><api:month>1</api:month><api:year>2011</api:year></api:date></api:field><api:field name="publication-status" type="text" display-name="Status"><api:text>Published</api:text></api:field><api:field name="record-created-at-source-date" type="date" display-name="Record created at source"><api:date><api:day>18</api:day><api:month>6</api:month><api:year>2010</api:year></api:date></api:field><api:field name="title" type="text" display-name="Title"><api:text>Models of cardiac tissue electrophysiology: progress, challenges and open questions.</api:text></api:field><api:field name="types" type="list" display-name="Sub types"><api:items><api:item>Research Support, Non-U.S. Gov't</api:item><api:item>Review</api:item><api:item>Research Support, U.S. Gov't, Non-P.H.S.</api:item><api:item>Journal Article</api:item></api:items></api:field><api:field name="volume" type="text" display-name="Volume"><api:text>104</api:text></api:field></api:native></api:record><api:record format="native" id="2470634" source-id="10" source-name="dimensions" source-display-name="Dimensions" id-at-source="pub.1021194689" last-modified-when="2024-04-28T23:23:26.063+01:00"><api:citation-count>455</api:citation-count><api:native><api:field name="altmetric-attention-score" type="integer" display-name="Altmetric attention score"><api:integer>1</api:integer></api:field><api:field name="associated-identifiers" type="identifier-list" display-name="Associated Identifiers"><api:identifiers><api:identifier scheme="dimensions-grant-id">grant.2996330</api:identifier><api:identifier scheme="dimensions-grant-id">grant.3091636</api:identifier></api:identifiers></api:field><api:field name="authors" type="person-list" display-name="Authors"><api:people><api:person><api:links><api:link type="elements/user" id="310" href="https://mypublications.shef.ac.uk:8091/secure-api/v6.13/users/310"/></api:links><api:last-name>Clayton</api:last-name><api:initials>RH</api:initials><api:first-names>RH</api:first-names><api:separate-first-names><api:first-name>R</api:first-name><api:first-name>H</api:first-name></api:separate-first-names><api:addresses><api:address iso-country-code="GB"><api:line type="organisation">University of Sheffield</api:line><api:line type="city">Sheffield</api:line><api:line type="country">United Kingdom</api:line></api:address></api:addresses><api:identifiers><api:identifier scheme="dimensions-researcher-id">ur.01320006245.84</api:identifier></api:identifiers><api:author-types><api:author-type>corresponding</api:author-type></api:author-types></api:person><api:person><api:last-name>Bernus</api:last-name><api:initials>O</api:initials><api:first-names>O</api:first-names><api:separate-first-names><api:first-name>O</api:first-name></api:separate-first-names><api:addresses><api:address iso-country-code="GB"><api:line type="organisation">University of Leeds</api:line><api:line type="city">Leeds</api:line><api:line type="country">United Kingdom</api:line></api:address></api:addresses><api:identifiers><api:identifier scheme="dimensions-researcher-id">ur.0673731357.60</api:identifier></api:identifiers></api:person><api:person><api:last-name>Cherry</api:last-name><api:initials>EM</api:initials><api:first-names>EM</api:first-names><api:separate-first-names><api:first-name>E</api:first-name><api:first-name>M</api:first-name></api:separate-first-names><api:addresses><api:address iso-country-code="US"><api:line type="organisation">Cornell University</api:line><api:line type="city">Ithaca</api:line><api:line type="state">New York</api:line><api:line type="country">United States</api:line></api:address></api:addresses><api:identifiers><api:identifier scheme="dimensions-researcher-id">ur.0577222713.79</api:identifier></api:identifiers></api:person><api:person><api:last-name>Dierckx</api:last-name><api:initials>H</api:initials><api:first-names>H</api:first-names><api:separate-first-names><api:first-name>H</api:first-name></api:separate-first-names><api:addresses><api:address iso-country-code="BE"><api:line type="organisation">Ghent University</api:line><api:line type="city">Ghent</api:line><api:line type="country">Belgium</api:line></api:address></api:addresses><api:identifiers><api:identifier scheme="dimensions-researcher-id">ur.01101304450.64</api:identifier></api:identifiers></api:person><api:person><api:last-name>Fenton</api:last-name><api:initials>FH</api:initials><api:first-names>FH</api:first-names><api:separate-first-names><api:first-name>F</api:first-name><api:first-name>H</api:first-name></api:separate-first-names><api:addresses><api:address iso-country-code="US"><api:line type="organisation">Cornell University</api:line><api:line type="city">Ithaca</api:line><api:line type="state">New York</api:line><api:line type="country">United States</api:line></api:address></api:addresses><api:identifiers><api:identifier scheme="dimensions-researcher-id">ur.01370436753.03</api:identifier></api:identifiers></api:person><api:person><api:last-name>Mirabella</api:last-name><api:initials>L</api:initials><api:first-names>L</api:first-names><api:separate-first-names><api:first-name>L</api:first-name></api:separate-first-names><api:addresses><api:address iso-country-code="US"><api:line type="organisation">Emory University</api:line><api:line type="city">Atlanta</api:line><api:line type="state">Georgia</api:line><api:line type="country">United States</api:line></api:address><api:address iso-country-code="IT"><api:line type="organisation">Politecnico di Milano</api:line><api:line type="city">Milan</api:line><api:line type="country">Italy</api:line></api:address></api:addresses><api:identifiers><api:identifier scheme="dimensions-researcher-id">ur.01353754366.38</api:identifier></api:identifiers></api:person><api:person><api:last-name>Panfilov</api:last-name><api:initials>AV</api:initials><api:first-names>AV</api:first-names><api:separate-first-names><api:first-name>A</api:first-name><api:first-name>V</api:first-name></api:separate-first-names><api:addresses><api:address iso-country-code="NL"><api:line type="organisation">Utrecht University</api:line><api:line type="city">Utrecht</api:line><api:line type="country">Netherlands</api:line></api:address></api:addresses><api:identifiers><api:identifier scheme="dimensions-researcher-id">ur.01044610725.13</api:identifier></api:identifiers></api:person><api:person><api:last-name>Sachse</api:last-name><api:initials>FB</api:initials><api:first-names>FB</api:first-names><api:separate-first-names><api:first-name>F</api:first-name><api:first-name>B</api:first-name></api:separate-first-names><api:addresses><api:address iso-country-code="US"><api:line type="organisation">University of Utah</api:line><api:line type="city">Salt Lake City</api:line><api:line type="state">Utah</api:line><api:line type="country">United States</api:line></api:address></api:addresses><api:identifiers><api:identifier scheme="dimensions-researcher-id">ur.01207637602.47</api:identifier></api:identifiers></api:person><api:person><api:last-name>Seemann</api:last-name><api:initials>G</api:initials><api:first-names>G</api:first-names><api:separate-first-names><api:first-name>G</api:first-name></api:separate-first-names><api:addresses><api:address iso-country-code="DE"><api:line type="organisation">Karlsruhe Institute of Technology</api:line><api:line type="city">Karlsruhe</api:line><api:line type="country">Germany</api:line></api:address></api:addresses><api:identifiers><api:identifier scheme="dimensions-researcher-id">ur.01350657425.41</api:identifier></api:identifiers></api:person><api:person><api:last-name>Zhang</api:last-name><api:initials>H</api:initials><api:first-names>H</api:first-names><api:separate-first-names><api:first-name>H</api:first-name></api:separate-first-names><api:addresses><api:address iso-country-code="GB"><api:line type="organisation">University of Manchester</api:line><api:line type="city">Manchester</api:line><api:line type="country">United Kingdom</api:line></api:address></api:addresses><api:identifiers><api:identifier scheme="dimensions-researcher-id">ur.0727423612.46</api:identifier></api:identifiers></api:person></api:people></api:field><api:field name="doi" type="text" display-name="DOI"><api:text>10.1016/j.pbiomolbio.2010.05.008</api:text><api:links><api:link type="doi" href="http://doi.org/10.1016/j.pbiomolbio.2010.05.008"/><api:link type="altmetric" href="http://www.altmetric.com/details.php?doi=10.1016/j.pbiomolbio.2010.05.008"/></api:links></api:field><api:field name="external-identifiers" type="identifier-list" display-name="External identifiers"><api:identifiers><api:identifier scheme="pubmed">20553746</api:identifier></api:identifiers></api:field><api:field name="field-citation-ratio" type="decimal" display-name="Field citation ratio"><api:decimal>38.2</api:decimal></api:field><api:field name="issn" type="text" display-name="ISSN"><api:text>0079-6107</api:text><api:links><api:link type="elements/journal" href="https://mypublications.shef.ac.uk:8091/secure-api/v6.13/journals/965661"/></api:links></api:field><api:field name="issue" type="text" display-name="Issue"><api:text>1-3</api:text></api:field><api:field name="journal" type="text" display-name="Journal"><api:text>Progress in Biophysics and Molecular Biology</api:text></api:field><api:field name="keywords" type="keyword-list" display-name="Keywords"><api:keywords><api:keyword scheme="for-2020">3101 Biochemistry and Cell Biology</api:keyword><api:keyword scheme="for-2020">31 Biological Sciences</api:keyword><api:keyword scheme="rcdc">Cardiovascular</api:keyword><api:keyword scheme="rcdc">Heart Disease</api:keyword><api:keyword scheme="rcdc">Networking and Information Technology R&amp;D (NITRD)</api:keyword><api:keyword scheme="rcdc">Bioengineering</api:keyword><api:keyword scheme="hrcs-hc">Cardiovascular</api:keyword><api:keyword scheme="mesh">Action Potentials</api:keyword><api:keyword scheme="mesh">Animals</api:keyword><api:keyword scheme="mesh">Cardiac Electrophysiology</api:keyword><api:keyword scheme="mesh">Cell Physiological Phenomena</api:keyword><api:keyword scheme="mesh">Forecasting</api:keyword><api:keyword scheme="mesh">Heart</api:keyword><api:keyword scheme="mesh">Humans</api:keyword><api:keyword scheme="mesh">Models, Cardiovascular</api:keyword><api:keyword scheme="mesh">Myocardium</api:keyword><api:keyword scheme="mesh">Rabbits</api:keyword></api:keywords></api:field><api:field name="online-publication-date" type="date" display-name="Online publication date"><api:date><api:day>27</api:day><api:month>5</api:month><api:year>2010</api:year></api:date></api:field><api:field name="open-access-status" type="text" display-name="Open access status"><api:text>Closed Access</api:text></api:field><api:field name="pagination" type="pagination" display-name="Pagination"><api:pagination><api:begin-page>22</api:begin-page><api:end-page>48</api:end-page></api:pagination></api:field><api:field name="publication-date" type="date" display-name="Publication date"><api:date><api:month>1</api:month><api:year>2011</api:year></api:date></api:field><api:field name="publisher" type="text" display-name="Publisher"><api:text>Elsevier</api:text></api:field><api:field name="record-created-at-source-date" type="date" display-name="Record created at source"><api:date><api:day>31</api:day><api:month>8</api:month><api:year>2017</api:year></api:date></api:field><api:field name="relative-citation-ratio" type="decimal" display-name="Relative citation ratio"><api:decimal>9.93</api:decimal></api:field><api:field name="title" type="text" display-name="Title"><api:text>Models of cardiac tissue electrophysiology: Progress, challenges and open questions</api:text></api:field><api:field name="volume" type="text" display-name="Volume"><api:text>104</api:text></api:field></api:native></api:record><api:record format="native" id="294038" source-id="11" source-name="wos-lite" source-display-name="Web of Science (Lite)" id-at-source="WOS:000287059100003" last-modified-when="2024-04-24T23:12:09.237+01:00"><api:citation-count>407</api:citation-count><api:native><api:field name="authors" type="person-list" display-name="Authors"><api:people><api:person><api:links><api:link type="elements/user" id="310" href="https://mypublications.shef.ac.uk:8091/secure-api/v6.13/users/310"/></api:links><api:last-name>Clayton</api:last-name><api:initials>RH</api:initials><api:first-names>RH</api:first-names><api:separate-first-names><api:first-name>R</api:first-name><api:first-name>H</api:first-name></api:separate-first-names></api:person><api:person><api:last-name>Bernus</api:last-name><api:initials>O</api:initials><api:first-names>O</api:first-names><api:separate-first-names><api:first-name>O</api:first-name></api:separate-first-names></api:person><api:person><api:last-name>Cherry</api:last-name><api:initials>EM</api:initials><api:first-names>EM</api:first-names><api:separate-first-names><api:first-name>E</api:first-name><api:first-name>M</api:first-name></api:separate-first-names></api:person><api:person><api:last-name>Dierckx</api:last-name><api:initials>H</api:initials><api:first-names>H</api:first-names><api:separate-first-names><api:first-name>H</api:first-name></api:separate-first-names></api:person><api:person><api:last-name>Fenton</api:last-name><api:initials>FH</api:initials><api:first-names>FH</api:first-names><api:separate-first-names><api:first-name>F</api:first-name><api:first-name>H</api:first-name></api:separate-first-names></api:person><api:person><api:last-name>Mirabella</api:last-name><api:initials>L</api:initials><api:first-names>L</api:first-names><api:separate-first-names><api:first-name>L</api:first-name></api:separate-first-names></api:person><api:person><api:last-name>Panfilov</api:last-name><api:initials>AV</api:initials><api:first-names>AV</api:first-names><api:separate-first-names><api:first-name>A</api:first-name><api:first-name>V</api:first-name></api:separate-first-names></api:person><api:person><api:last-name>Sachse</api:last-name><api:initials>FB</api:initials><api:first-names>FB</api:first-names><api:separate-first-names><api:first-name>F</api:first-name><api:first-name>B</api:first-name></api:separate-first-names></api:person><api:person><api:last-name>Seemann</api:last-name><api:initials>G</api:initials><api:first-names>G</api:first-names><api:separate-first-names><api:first-name>G</api:first-name></api:separate-first-names></api:person><api:person><api:last-name>Zhang</api:last-name><api:initials>H</api:initials><api:first-names>H</api:first-names><api:separate-first-names><api:first-name>H</api:first-name></api:separate-first-names></api:person></api:people></api:field><api:field name="author-url" type="text" display-name="Link 1"><api:text>https://www.webofscience.com/api/gateway?GWVersion=2&amp;SrcApp=sheffield_elements_live&amp;SrcAuth=WosAPI&amp;KeyUT=WOS:000287059100003&amp;DestLinkType=FullRecord&amp;DestApp=WOS_CPL</api:text></api:field><api:field name="doi" type="text" display-name="DOI"><api:text>10.1016/j.pbiomolbio.2010.05.008</api:text><api:links><api:link type="doi" href="http://doi.org/10.1016/j.pbiomolbio.2010.05.008"/><api:link type="altmetric" href="http://www.altmetric.com/details.php?doi=10.1016/j.pbiomolbio.2010.05.008"/></api:links></api:field><api:field name="external-identifiers" type="identifier-list" display-name="External identifiers"><api:identifiers><api:identifier scheme="isidoc">717PE</api:identifier><api:identifier scheme="pubmed">20553746</api:identifier></api:identifiers></api:field><api:field name="issn" type="text" display-name="ISSN"><api:text>0079-6107</api:text><api:links><api:link type="elements/journal" href="https://mypublications.shef.ac.uk:8091/secure-api/v6.13/journals/965661"/></api:links></api:field><api:field name="issue" type="text" display-name="Issue"><api:text>1-3</api:text></api:field><api:field name="journal" type="text" display-name="Journal"><api:text>PROGRESS IN BIOPHYSICS &amp; MOLECULAR BIOLOGY</api:text></api:field><api:field name="keywords" type="keyword-list" display-name="Keywords"><api:keywords><api:keyword>Computer model</api:keyword><api:keyword>Cardiac tissue</api:keyword><api:keyword>Electrophysiology</api:keyword><api:keyword>Heart</api:keyword><api:keyword>Review</api:keyword></api:keywords></api:field><api:field name="pagination" type="pagination" display-name="Pagination"><api:pagination><api:begin-page>22</api:begin-page><api:end-page>48</api:end-page></api:pagination></api:field><api:field name="publication-date" type="date" display-name="Publication date"><api:date><api:year>2011</api:year></api:date></api:field><api:field name="publication-status" type="text" display-name="Status"><api:text>Published</api:text></api:field><api:field name="title" type="text" display-name="Title"><api:text>Models of cardiac tissue electrophysiology: Progress, challenges and open questions</api:text></api:field><api:field name="types" type="list" display-name="Sub types"><api:items><api:item>Review</api:item></api:items></api:field><api:field name="volume" type="text" display-name="Volume"><api:text>104</api:text></api:field></api:native></api:record><api:record format="native" id="161828" source-id="3" source-name="wos" source-display-name="Web of Science" id-at-source="WOS:000287059100003" last-modified-when="2014-07-25T17:06:10.28+01:00"><api:citation-count>6</api:citation-count><api:native><api:field name="authors" type="person-list" display-name="Authors"><api:people><api:person><api:links><api:link type="elements/user" id="310" href="https://mypublications.shef.ac.uk:8091/secure-api/v6.13/users/310"/></api:links><api:last-name>Clayton</api:last-name><api:initials>RH</api:initials><api:first-names>RH</api:first-names><api:separate-first-names><api:first-name>R</api:first-name><api:first-name>H</api:first-name></api:separate-first-names><api:addresses><api:address iso-country-code="GB"><api:line type="full">Univ Sheffield, Dept Comp Sci, Sheffield S1 4DP, S Yorkshire, England</api:line></api:address></api:addresses></api:person><api:person><api:last-name>Bernus</api:last-name><api:initials>O</api:initials><api:first-names>O</api:first-names><api:separate-first-names><api:first-name>O</api:first-name></api:separate-first-names><api:addresses><api:address iso-country-code="GB"><api:line type="full">Univ Leeds, Multidisciplinary Cardiovasc Res Ctr, Inst Membrane &amp; Syst Biol, Leeds LS2 9JT, W Yorkshire, England</api:line></api:address></api:addresses></api:person><api:person><api:last-name>Cherry</api:last-name><api:initials>EM</api:initials><api:first-names>EM</api:first-names><api:separate-first-names><api:first-name>E</api:first-name><api:first-name>M</api:first-name></api:separate-first-names><api:addresses><api:address iso-country-code="US"><api:line type="full">Cornell Univ, Dept Biomed Sci, Ithaca, NY USA</api:line></api:address></api:addresses></api:person><api:person><api:last-name>Dierckx</api:last-name><api:initials>H</api:initials><api:first-names>H</api:first-names><api:separate-first-names><api:first-name>H</api:first-name></api:separate-first-names><api:addresses><api:address iso-country-code="BE"><api:line type="full">Univ Ghent, Dept Phys &amp; Astron, Ghent, Belgium</api:line></api:address></api:addresses></api:person><api:person><api:last-name>Fenton</api:last-name><api:initials>FH</api:initials><api:first-names>FH</api:first-names><api:separate-first-names><api:first-name>F</api:first-name><api:first-name>H</api:first-name></api:separate-first-names><api:addresses><api:address iso-country-code="US"><api:line type="full">Cornell Univ, Dept Biomed Sci, Ithaca, NY USA</api:line></api:address></api:addresses></api:person><api:person><api:last-name>Mirabella</api:last-name><api:initials>L</api:initials><api:first-names>L</api:first-names><api:separate-first-names><api:first-name>L</api:first-name></api:separate-first-names><api:addresses><api:address iso-country-code="US"><api:line type="full">Emory Univ, Dept Math &amp; Comp Sci, Atlanta, GA 30322 USA</api:line></api:address></api:addresses></api:person><api:person><api:last-name>Panfilov</api:last-name><api:initials>AV</api:initials><api:first-names>AV</api:first-names><api:separate-first-names><api:first-name>A</api:first-name><api:first-name>V</api:first-name></api:separate-first-names><api:addresses><api:address iso-country-code="NL"><api:line type="full">Univ Utrecht, Dept Theoret Biol, NL-3508 TC Utrecht, Netherlands</api:line></api:address></api:addresses></api:person><api:person><api:last-name>Sachse</api:last-name><api:initials>FB</api:initials><api:first-names>FB</api:first-names><api:separate-first-names><api:first-name>F</api:first-name><api:first-name>B</api:first-name></api:separate-first-names><api:addresses><api:address iso-country-code="US"><api:line type="full">Univ Utah, Dept Bioengn, Salt Lake City, UT 84112 USA</api:line></api:address></api:addresses></api:person><api:person><api:last-name>Seemann</api:last-name><api:initials>G</api:initials><api:first-names>G</api:first-names><api:separate-first-names><api:first-name>G</api:first-name></api:separate-first-names><api:addresses><api:address iso-country-code="DE"><api:line type="full">Karlsruhe Inst Technol, Inst Biomed Engn, Karlsruhe, Germany</api:line></api:address></api:addresses></api:person><api:person><api:last-name>Zhang</api:last-name><api:initials>H</api:initials><api:first-names>H</api:first-names><api:separate-first-names><api:first-name>H</api:first-name></api:separate-first-names><api:addresses><api:address iso-country-code="GB"><api:line type="full">Univ Manchester, Dept Phys, Manchester M13 9PL, Lancs, England</api:line></api:address></api:addresses></api:person></api:people></api:field><api:field name="doi" type="text" display-name="DOI"><api:text>10.1016/j.pbiomolbio.2010.05.008</api:text><api:links><api:link type="doi" href="http://doi.org/10.1016/j.pbiomolbio.2010.05.008"/><api:link type="altmetric" href="http://www.altmetric.com/details.php?doi=10.1016/j.pbiomolbio.2010.05.008"/></api:links></api:field><api:field name="issn" type="text" display-name="ISSN"><api:text>0079-6107</api:text><api:links><api:link type="elements/journal" href="https://mypublications.shef.ac.uk:8091/secure-api/v6.13/journals/965661"/></api:links></api:field><api:field name="issue" type="text" display-name="Issue"><api:text>1-3</api:text></api:field><api:field name="journal" type="text" display-name="Journal"><api:text>PROG BIOPHYS MOL BIO</api:text></api:field><api:field name="keywords" type="keyword-list" display-name="Keywords"><api:keywords><api:keyword>Computer model</api:keyword><api:keyword>Cardiac tissue</api:keyword><api:keyword>Electrophysiology</api:keyword><api:keyword>Heart</api:keyword><api:keyword>Review</api:keyword><api:keyword>ACTION-POTENTIAL DURATION</api:keyword><api:keyword>COMPUTER 3-DIMENSIONAL RECONSTRUCTION</api:keyword><api:keyword>CONDUCTION-VELOCITY RESTITUTION</api:keyword><api:keyword>MYOCARDIAL FIBER-ORIENTATION</api:keyword><api:keyword>REACTION-DIFFUSION SYSTEMS</api:keyword><api:keyword>ADAPTIVE MESH REFINEMENT</api:keyword><api:keyword>HUMAN VENTRICULAR CELLS</api:keyword><api:keyword>FINITE-ELEMENT-METHOD</api:keyword><api:keyword>HUMAN ATRIAL CELL</api:keyword><api:keyword>BIDOMAIN MODEL</api:keyword></api:keywords></api:field><api:field name="pagination" type="pagination" display-name="Pagination"><api:pagination><api:begin-page>22</api:begin-page><api:end-page>48</api:end-page></api:pagination></api:field><api:field name="publication-date" type="date" display-name="Publication date"><api:date><api:month>1</api:month><api:year>2011</api:year></api:date></api:field><api:field name="title" type="text" display-name="Title"><api:text>Models of cardiac tissue electrophysiology: Progress, challenges and open questions</api:text></api:field><api:field name="volume" type="text" display-name="Volume"><api:text>104</api:text></api:field></api:native></api:record></api:records><api:fields/><api:all-labels type="keyword-list"><api:keywords><api:keyword scheme="mesh" origin="record-data" source="pubmed">Action Potentials</api:keyword><api:keyword scheme="mesh" origin="record-data" source="pubmed">Animals</api:keyword><api:keyword scheme="mesh" origin="record-data" source="pubmed">Cardiac Electrophysiology</api:keyword><api:keyword scheme="mesh" origin="record-data" source="pubmed">Cell Physiological Phenomena</api:keyword><api:keyword scheme="mesh" origin="record-data" source="pubmed">Forecasting</api:keyword><api:keyword scheme="mesh" origin="record-data" source="pubmed">Heart</api:keyword><api:keyword scheme="mesh" origin="record-data" source="pubmed">Humans</api:keyword><api:keyword scheme="mesh" origin="record-data" source="pubmed">Models, Cardiovascular</api:keyword><api:keyword scheme="mesh" origin="record-data" source="pubmed">Myocardium</api:keyword><api:keyword scheme="mesh" origin="record-data" source="pubmed">Rabbits</api:keyword><api:keyword scheme="mesh" origin="record-data" source="epmc">Myocardium</api:keyword><api:keyword scheme="mesh" origin="record-data" source="epmc">Heart</api:keyword><api:keyword scheme="mesh" origin="record-data" source="epmc">Animals</api:keyword><api:keyword scheme="mesh" origin="record-data" source="epmc">Rabbits</api:keyword><api:keyword scheme="mesh" origin="record-data" source="epmc">Humans</api:keyword><api:keyword scheme="mesh" origin="record-data" source="epmc">Action Potentials</api:keyword><api:keyword scheme="mesh" origin="record-data" source="epmc">Models, Cardiovascular</api:keyword><api:keyword scheme="mesh" origin="record-data" source="epmc">Forecasting</api:keyword><api:keyword scheme="mesh" origin="record-data" source="epmc">Cardiac Electrophysiology</api:keyword><api:keyword scheme="mesh" origin="record-data" source="epmc">Cell Physiological Phenomena</api:keyword><api:keyword scheme="for-2020" origin="record-data" source="dimensions">3101 Biochemistry and Cell Biology</api:keyword><api:keyword scheme="for-2020" origin="record-data" source="dimensions">31 Biological Sciences</api:keyword><api:keyword scheme="rcdc" origin="record-data" source="dimensions">Cardiovascular</api:keyword><api:keyword scheme="rcdc" origin="record-data" source="dimensions">Heart Disease</api:keyword><api:keyword scheme="rcdc" origin="record-data" source="dimensions">Networking and Information Technology R&amp;D (NITRD)</api:keyword><api:keyword scheme="rcdc" origin="record-data" source="dimensions">Bioengineering</api:keyword><api:keyword scheme="hrcs-hc" origin="record-data" source="dimensions">Cardiovascular</api:keyword><api:keyword scheme="mesh" origin="record-data" source="dimensions">Action Potentials</api:keyword><api:keyword scheme="mesh" origin="record-data" source="dimensions">Animals</api:keyword><api:keyword scheme="mesh" origin="record-data" source="dimensions">Cardiac Electrophysiology</api:keyword><api:keyword scheme="mesh" origin="record-data" source="dimensions">Cell Physiological Phenomena</api:keyword><api:keyword scheme="mesh" origin="record-data" source="dimensions">Forecasting</api:keyword><api:keyword scheme="mesh" origin="record-data" source="dimensions">Heart</api:keyword><api:keyword scheme="mesh" origin="record-data" source="dimensions">Humans</api:keyword><api:keyword scheme="mesh" origin="record-data" source="dimensions">Models, Cardiovascular</api:keyword><api:keyword scheme="mesh" origin="record-data" source="dimensions">Myocardium</api:keyword><api:keyword scheme="mesh" origin="record-data" source="dimensions">Rabbits</api:keyword><api:keyword origin="record-data" source="wos-lite">Computer model</api:keyword><api:keyword origin="record-data" source="wos-lite">Cardiac tissue</api:keyword><api:keyword origin="record-data" source="wos-lite">Electrophysiology</api:keyword><api:keyword origin="record-data" source="wos-lite">Heart</api:keyword><api:keyword origin="record-data" source="wos-lite">Review</api:keyword><api:keyword origin="record-data" source="wos">Computer model</api:keyword><api:keyword origin="record-data" source="wos">Cardiac tissue</api:keyword><api:keyword origin="record-data" source="wos">Electrophysiology</api:keyword><api:keyword origin="record-data" source="wos">Heart</api:keyword><api:keyword origin="record-data" source="wos">Review</api:keyword><api:keyword origin="record-data" source="wos">ACTION-POTENTIAL DURATION</api:keyword><api:keyword origin="record-data" source="wos">COMPUTER 3-DIMENSIONAL RECONSTRUCTION</api:keyword><api:keyword origin="record-data" source="wos">CONDUCTION-VELOCITY RESTITUTION</api:keyword><api:keyword origin="record-data" source="wos">MYOCARDIAL FIBER-ORIENTATION</api:keyword><api:keyword origin="record-data" source="wos">REACTION-DIFFUSION SYSTEMS</api:keyword><api:keyword origin="record-data" source="wos">ADAPTIVE MESH REFINEMENT</api:keyword><api:keyword origin="record-data" source="wos">HUMAN VENTRICULAR CELLS</api:keyword><api:keyword origin="record-data" source="wos">FINITE-ELEMENT-METHOD</api:keyword><api:keyword origin="record-data" source="wos">HUMAN ATRIAL CELL</api:keyword><api:keyword origin="record-data" source="wos">BIDOMAIN MODEL</api:keyword><api:keyword scheme="for" origin="issn-inferred">0601 Biochemistry and Cell Biology</api:keyword><api:keyword scheme="science-metrix" origin="issn-inferred">Biophysics</api:keyword><api:keyword scheme="for-2020" origin="issn-inferred">3101 Biochemistry and cell biology</api:keyword></api:keywords></api:all-labels><api:journal issn="0079-6107" href="https://mypublications.shef.ac.uk:8091/secure-api/v6.13/journals/965661" title="Progress in Biophysics and Molecular Biology"><api:records><api:record source-name="summary"><api:title>Progress in Biophysics and Molecular Biology</api:title></api:record></api:records></api:journal><api:relationships href="https://mypublications.shef.ac.uk:8091/secure-api/v6.13/publications/57571/relationships"/></api:object></api:result></api:response>