<?xml version="1.0" encoding="utf-8"?><api:response xmlns:api="http://www.symplectic.co.uk/publications/api"><api:version uri="https://mypublications.shef.ac.uk/" elements-version="6.15.0.3976" schema-version="6.13" product-name="myPublications"/><api:request href="https://mypublications.shef.ac.uk:8091/secure-api/v6.13/publications/373"/><api:result><api:object category="publication" id="373" last-affected-when="2024-04-10T00:07:08.04+01:00" last-modified-when="2024-04-10T00:07:08.04+01:00" href="https://mypublications.shef.ac.uk:8091/secure-api/v6.13/publications/373" created-when="2010-05-17T13:46:18.46+01:00" type-id="5" type-display-name="Journal article" type="journal-article"><api:privacy-level>Public</api:privacy-level><api:privacy-level-locked>false</api:privacy-level-locked><api:ever-approved>true</api:ever-approved><api:reporting-date-1>1999-05-28</api:reporting-date-1><api:allow-type-switching>true</api:allow-type-switching><api:records><api:record format="native" id="1518193" source-id="13" source-name="crossref" source-display-name="Crossref" id-at-source="10.1016/S0165-1838(99)00016-8" last-modified-when="2022-09-11T06:50:48.12+01:00"><api:native><api:field name="authors" type="person-list" display-name="Authors"><api:people><api:person><api:last-name>Hillsley</api:last-name><api:initials>K</api:initials><api:first-names>K</api:first-names><api:separate-first-names><api:first-name>K</api:first-name></api:separate-first-names></api:person><api:person><api:links><api:link type="elements/user" id="2035" href="https://mypublications.shef.ac.uk:8091/secure-api/v6.13/users/2035"/></api:links><api:last-name>Grundy</api:last-name><api:initials>D</api:initials><api:first-names>D</api:first-names><api:separate-first-names><api:first-name>D</api:first-name></api:separate-first-names></api:person></api:people></api:field><api:field name="doi" type="text" display-name="DOI"><api:text>10.1016/s0165-1838(99)00016-8</api:text><api:links><api:link type="doi" href="http://doi.org/10.1016/s0165-1838(99)00016-8"/><api:link type="altmetric" href="http://www.altmetric.com/details.php?doi=10.1016/s0165-1838(99)00016-8"/></api:links></api:field><api:field name="issn" type="text" display-name="ISSN"><api:text>0165-1838</api:text><api:links><api:link type="elements/journal" href="https://mypublications.shef.ac.uk:8091/secure-api/v6.13/journals/984697"/></api:links></api:field><api:field name="issue" type="text" display-name="Issue"><api:text>2-3</api:text></api:field><api:field name="journal" type="text" display-name="Journal"><api:text>Journal of the Autonomic Nervous System</api:text></api:field><api:field name="language" type="text" display-name="Language"><api:text>en</api:text></api:field><api:field name="pagination" type="pagination" display-name="Pagination"><api:pagination><api:begin-page>93</api:begin-page><api:end-page>98</api:end-page></api:pagination></api:field><api:field name="publication-date" type="date" display-name="Publication date"><api:date><api:month>5</api:month><api:year>1999</api:year></api:date></api:field><api:field name="publication-status" type="text" display-name="Status"><api:text>Published</api:text></api:field><api:field name="publisher" type="text" display-name="Publisher"><api:text>Elsevier BV</api:text></api:field><api:field name="publisher-url" type="text" display-name="Link 2"><api:text>http://dx.doi.org/10.1016/s0165-1838(99)00016-8</api:text></api:field><api:field name="record-created-at-source-date" type="date" display-name="Record created at source"><api:date><api:day>29</api:day><api:month>1</api:month><api:year>2020</api:year></api:date></api:field><api:field name="title" type="text" display-name="Title"><api:text>Plasticity in the mesenteric afferent response to cisplatin following vagotomy in the rat</api:text></api:field><api:field name="volume" type="text" display-name="Volume"><api:text>76</api:text></api:field></api:native></api:record><api:record format="native" id="94789" source-id="7" source-name="scopus" source-display-name="Scopus" id-at-source="2-s2.0-0033065820" last-modified-when="2024-04-10T00:07:08.097+01:00"><api:citation-count>26</api:citation-count><api:native><api:field name="abstract" type="text" display-name="Abstract"><api:text>The aim of this study was to investigate the actions of the cytotoxic drug cisplatin on populations of mesenteric afferents supplying the rat jejunum. Extracellular whole mesenteric nerve discharge was monitored and the activity of individual single afferent units determined using waveform discriminator software. Baseline whole nerve discharge was 21.5 ± 3.8 impulses s-1. Nerve discharge began to increase approximately 10 min after cisplatin administration, reached a plateau around 30 min, and remained elevated at 60 min (35.3 ± 5.7 impulses s-1, p &lt; 0.01). Granisetron reversed the increase in nerve activity indicating that the response to cisplatin was mediated by the release of endogenous 5-HT acting on 5-HT3 receptors. Single afferent units, selected by waveform analysis on the basis of their response to exogenous 5-HT, showed a similar time course of activation following cisplatin. In contrast, the discharge frequency of afferent units that were insensitive to 5-HT was unaffected by cisplatin or granisetron. The sensitivity of mesenteric afferent bundles to exogenous 5-HT was absent in chronically vagotomized animals. However, cisplatin elicited an increase in nerve discharge in vagotomized animals that was not different from control (34.6 ± 8.9 impulses s-1) but this increase was unaffected by treatment with granisetron. Thus, after vagotomy there is a switch from 5-HT3 mediated activation of vagal afferents to a 5-HT3-independent activation of non-vagal (possibly splanchnic) afferents. Since this later mechanism of activation is absent in control animals, it appears that there is plasticity in the gastrointestinal afferent sensitivity to cisplatin.</api:text></api:field><api:field name="authors" type="person-list" display-name="Authors"><api:people><api:person><api:last-name>Hillsley</api:last-name><api:initials>K</api:initials><api:first-names>K</api:first-names><api:separate-first-names><api:first-name>K</api:first-name></api:separate-first-names><api:addresses><api:address iso-country-code="GB"><api:line type="organisation">The University of Sheffield</api:line><api:line type="city">Sheffield</api:line><api:line type="country">United Kingdom</api:line></api:address><api:address iso-country-code="US"><api:line type="organisation">University of Nevada, Reno</api:line><api:line type="city">Reno</api:line><api:line type="country">United States</api:line></api:address></api:addresses><api:identifiers><api:identifier scheme="scopus-author-id">6701754367</api:identifier></api:identifiers></api:person><api:person><api:links><api:link type="elements/user" id="2035" href="https://mypublications.shef.ac.uk:8091/secure-api/v6.13/users/2035"/></api:links><api:last-name>Grundy</api:last-name><api:initials>D</api:initials><api:first-names>D</api:first-names><api:separate-first-names><api:first-name>D</api:first-name></api:separate-first-names><api:addresses><api:address iso-country-code="GB"><api:line type="organisation">The University of Sheffield</api:line><api:line type="city">Sheffield</api:line><api:line type="country">United Kingdom</api:line></api:address></api:addresses><api:identifiers><api:identifier scheme="scopus-author-id">35291918000</api:identifier></api:identifiers></api:person></api:people></api:field><api:field name="doi" type="text" display-name="DOI"><api:text>10.1016/S0165-1838(99)00016-8</api:text><api:links><api:link type="doi" href="http://doi.org/10.1016/S0165-1838(99)00016-8"/><api:link type="altmetric" href="http://www.altmetric.com/details.php?doi=10.1016/S0165-1838(99)00016-8"/></api:links></api:field><api:field name="external-identifiers" type="identifier-list" display-name="External identifiers"><api:identifiers><api:identifier scheme="pubmed">10412832</api:identifier></api:identifiers></api:field><api:field name="issn" type="text" display-name="ISSN"><api:text>0165-1838</api:text><api:links><api:link type="elements/journal" href="https://mypublications.shef.ac.uk:8091/secure-api/v6.13/journals/984697"/></api:links></api:field><api:field name="issue" type="text" display-name="Issue"><api:text>2-3</api:text></api:field><api:field name="journal" type="text" display-name="Journal"><api:text>Journal of the Autonomic Nervous System</api:text></api:field><api:field name="pagination" type="pagination" display-name="Pagination"><api:pagination><api:begin-page>93</api:begin-page><api:end-page>98</api:end-page></api:pagination></api:field><api:field name="publication-date" type="date" display-name="Publication date"><api:date><api:day>28</api:day><api:month>5</api:month><api:year>1999</api:year></api:date></api:field><api:field name="publication-status" type="text" display-name="Status"><api:text>Published</api:text></api:field><api:field name="title" type="text" display-name="Title"><api:text>Plasticity in the mesenteric afferent response to cisplatin following vagotomy in the rat</api:text></api:field><api:field name="types" type="list" display-name="Sub types"><api:items><api:item>Journal Article</api:item></api:items></api:field><api:field name="volume" type="text" display-name="Volume"><api:text>76</api:text></api:field></api:native></api:record><api:record format="native" id="373" source-id="2" source-name="pubmed" source-display-name="PubMed" id-at-source="10412832" last-modified-when="2020-04-29T04:25:27.937+01:00"><api:native><api:field name="abstract" type="text" display-name="Abstract"><api:text>The aim of this study was to investigate the actions of the cytotoxic drug cisplatin on populations of mesenteric afferents supplying the rat jejunum. Extracellular whole mesenteric nerve discharge was monitored and the activity of individual single afferent units determined using waveform discriminator software. Baseline whole nerve discharge was 21.5 +/- 3.8 impulses s(-1). Nerve discharge began to increase approximately 10 min after cisplatin administration, reached a plateau around 30 min, and remained elevated at 60 min (35.3 +/- 5.7 impulses s(-1), p &lt; 0.01). Granisetron reversed the increase in nerve activity indicating that the response to cisplatin was mediated by the release of endogenous 5-HT acting on 5-HT3 receptors. Single afferent units, selected by waveform analysis on the basis of their response to exogenous 5-HT, showed a similar time course of activation following cisplatin. In contrast, the discharge frequency of afferent units that were insensitive to 5-HT was unaffected by cisplatin or granisetron. The sensitivity of mesenteric afferent bundles to exogenous 5-HT was absent in chronically vagotomized animals. However, cisplatin elicited an increase in nerve discharge in vagotomized animals that was not different from control (34.6 +/- 8.9 impulses s(-1)) but this increase was unaffected by treatment with granisetron. Thus, after vagotomy there is a switch from 5-HT3 mediated activation of vagal afferents to a 5-HT3-independent activation of non-vagal (possibly splanchnic) afferents. Since this later mechanism of activation is absent in control animals, it appears that there is plasticity in the gastrointestinal afferent sensitivity to cisplatin.</api:text></api:field><api:field name="authors" type="person-list" display-name="Authors"><api:people><api:person><api:last-name>Hillsley</api:last-name><api:initials>K</api:initials><api:first-names>K</api:first-names><api:separate-first-names><api:first-name>K</api:first-name></api:separate-first-names><api:addresses><api:address iso-country-code="GB"><api:line type="full">Department of Biomedical Science, University of Sheffield, Western Bank, UK.</api:line></api:address></api:addresses></api:person><api:person><api:links><api:link type="elements/user" id="2035" href="https://mypublications.shef.ac.uk:8091/secure-api/v6.13/users/2035"/></api:links><api:last-name>Grundy</api:last-name><api:initials>D</api:initials><api:first-names>D</api:first-names><api:separate-first-names><api:first-name>D</api:first-name></api:separate-first-names></api:person></api:people></api:field><api:field name="author-url" type="text" display-name="Link 1"><api:text>https://www.ncbi.nlm.nih.gov/pubmed/10412832</api:text></api:field><api:field name="doi" type="text" display-name="DOI"><api:text>10.1016/s0165-1838(99)00016-8</api:text><api:links><api:link type="doi" href="http://doi.org/10.1016/s0165-1838(99)00016-8"/><api:link type="altmetric" href="http://www.altmetric.com/details.php?doi=10.1016/s0165-1838(99)00016-8"/></api:links></api:field><api:field name="issn" type="text" display-name="ISSN"><api:text>0165-1838</api:text><api:links><api:link type="elements/journal" href="https://mypublications.shef.ac.uk:8091/secure-api/v6.13/journals/984697"/></api:links></api:field><api:field name="issue" type="text" display-name="Issue"><api:text>2-3</api:text></api:field><api:field name="journal" type="text" display-name="Journal"><api:text>J Auton Nerv Syst</api:text></api:field><api:field name="keywords" type="keyword-list" display-name="Keywords"><api:keywords><api:keyword scheme="mesh">Animals</api:keyword><api:keyword scheme="mesh">Cisplatin</api:keyword><api:keyword scheme="mesh">Electric Stimulation</api:keyword><api:keyword scheme="mesh">Granisetron</api:keyword><api:keyword scheme="mesh">Jejunum</api:keyword><api:keyword scheme="mesh">Male</api:keyword><api:keyword scheme="mesh">Mesentery</api:keyword><api:keyword scheme="mesh">Neuronal Plasticity</api:keyword><api:keyword scheme="mesh">Neurons, Afferent</api:keyword><api:keyword scheme="mesh">Rats</api:keyword><api:keyword scheme="mesh">Rats, Wistar</api:keyword><api:keyword scheme="mesh">Serotonin</api:keyword><api:keyword scheme="mesh">Serotonin Antagonists</api:keyword><api:keyword scheme="mesh">Vagotomy</api:keyword></api:keywords></api:field><api:field name="language" type="text" display-name="Language"><api:text>eng</api:text></api:field><api:field name="location" type="text" display-name="Country"><api:text>Netherlands</api:text></api:field><api:field name="pagination" type="pagination" display-name="Pagination"><api:pagination><api:begin-page>93</api:begin-page><api:end-page>98</api:end-page></api:pagination></api:field><api:field name="pii" type="text" display-name="PII"><api:text>S0165-1838(99)00016-8</api:text></api:field><api:field name="publication-date" type="date" display-name="Publication date"><api:date><api:day>28</api:day><api:month>5</api:month><api:year>1999</api:year></api:date></api:field><api:field name="publication-status" type="text" display-name="Status"><api:text>Published</api:text></api:field><api:field name="record-made-public-at-source-date" type="date" display-name="Record made publicly available"><api:date><api:day>1</api:day><api:month>9</api:month><api:year>1999</api:year></api:date></api:field><api:field name="title" type="text" display-name="Title"><api:text>Plasticity in the mesenteric afferent response to cisplatin following vagotomy in the rat.</api:text></api:field><api:field name="types" type="list" display-name="Sub types"><api:items><api:item>Journal Article</api:item><api:item>Research Support, Non-U.S. Gov't</api:item></api:items></api:field><api:field name="volume" type="text" display-name="Volume"><api:text>76</api:text></api:field></api:native></api:record><api:record format="native" id="881781" source-id="18" source-name="epmc" source-display-name="Europe PubMed Central" id-at-source="MED:10412832" last-modified-when="2021-07-06T17:34:55.267+01:00"><api:citation-count>17</api:citation-count><api:native><api:field name="abstract" type="text" display-name="Abstract"><api:text>The aim of this study was to investigate the actions of the cytotoxic drug cisplatin on populations of mesenteric afferents supplying the rat jejunum. Extracellular whole mesenteric nerve discharge was monitored and the activity of individual single afferent units determined using waveform discriminator software. Baseline whole nerve discharge was 21.5 +/- 3.8 impulses s(-1). Nerve discharge began to increase approximately 10 min after cisplatin administration, reached a plateau around 30 min, and remained elevated at 60 min (35.3 +/- 5.7 impulses s(-1), p &lt; 0.01). Granisetron reversed the increase in nerve activity indicating that the response to cisplatin was mediated by the release of endogenous 5-HT acting on 5-HT3 receptors. Single afferent units, selected by waveform analysis on the basis of their response to exogenous 5-HT, showed a similar time course of activation following cisplatin. In contrast, the discharge frequency of afferent units that were insensitive to 5-HT was unaffected by cisplatin or granisetron. The sensitivity of mesenteric afferent bundles to exogenous 5-HT was absent in chronically vagotomized animals. However, cisplatin elicited an increase in nerve discharge in vagotomized animals that was not different from control (34.6 +/- 8.9 impulses s(-1)) but this increase was unaffected by treatment with granisetron. Thus, after vagotomy there is a switch from 5-HT3 mediated activation of vagal afferents to a 5-HT3-independent activation of non-vagal (possibly splanchnic) afferents. Since this later mechanism of activation is absent in control animals, it appears that there is plasticity in the gastrointestinal afferent sensitivity to cisplatin.</api:text></api:field><api:field name="addresses" type="address-list" display-name="Addresses"><api:addresses><api:address iso-country-code="GB"><api:line type="full">Department of Biomedical Science, University of Sheffield, Western Bank, UK.</api:line></api:address></api:addresses></api:field><api:field name="authors" type="person-list" display-name="Authors"><api:people><api:person><api:last-name>Hillsley</api:last-name><api:initials>K</api:initials><api:first-names>K</api:first-names><api:separate-first-names><api:first-name>K</api:first-name></api:separate-first-names></api:person><api:person><api:links><api:link type="elements/user" id="2035" href="https://mypublications.shef.ac.uk:8091/secure-api/v6.13/users/2035"/></api:links><api:last-name>Grundy</api:last-name><api:initials>D</api:initials><api:first-names>D</api:first-names><api:separate-first-names><api:first-name>D</api:first-name></api:separate-first-names></api:person></api:people></api:field><api:field name="doi" type="text" display-name="DOI"><api:text>10.1016/s0165-1838(99)00016-8</api:text><api:links><api:link type="doi" href="http://doi.org/10.1016/s0165-1838(99)00016-8"/><api:link type="altmetric" href="http://www.altmetric.com/details.php?doi=10.1016/s0165-1838(99)00016-8"/></api:links></api:field><api:field name="external-identifiers" type="identifier-list" display-name="External identifiers"><api:identifiers><api:identifier scheme="pubmed">10412832</api:identifier></api:identifiers></api:field><api:field name="is-open-access" type="boolean" display-name="Open access"><api:boolean>false</api:boolean></api:field><api:field name="issn" type="text" display-name="ISSN"><api:text>0165-1838</api:text><api:links><api:link type="elements/journal" href="https://mypublications.shef.ac.uk:8091/secure-api/v6.13/journals/984697"/></api:links></api:field><api:field name="issue" type="text" display-name="Issue"><api:text>2-3</api:text></api:field><api:field name="journal" type="text" display-name="Journal"><api:text>Journal of the autonomic nervous system</api:text></api:field><api:field name="keywords" type="keyword-list" display-name="Keywords"><api:keywords><api:keyword scheme="mesh">Mesentery</api:keyword><api:keyword scheme="mesh">Jejunum</api:keyword><api:keyword scheme="mesh">Neurons, Afferent</api:keyword><api:keyword scheme="mesh">Animals</api:keyword><api:keyword scheme="mesh">Rats</api:keyword><api:keyword scheme="mesh">Rats, Wistar</api:keyword><api:keyword scheme="mesh">Cisplatin</api:keyword><api:keyword scheme="mesh">Serotonin</api:keyword><api:keyword scheme="mesh">Granisetron</api:keyword><api:keyword scheme="mesh">Serotonin Antagonists</api:keyword><api:keyword scheme="mesh">Vagotomy</api:keyword><api:keyword scheme="mesh">Electric Stimulation</api:keyword><api:keyword scheme="mesh">Neuronal Plasticity</api:keyword><api:keyword scheme="mesh">Male</api:keyword></api:keywords></api:field><api:field name="language" type="text" display-name="Language"><api:text>eng</api:text></api:field><api:field name="medium" type="text" display-name="Medium"><api:text>Print</api:text></api:field><api:field name="pagination" type="pagination" display-name="Pagination"><api:pagination><api:begin-page>93</api:begin-page><api:end-page>98</api:end-page></api:pagination></api:field><api:field name="publication-date" type="date" display-name="Publication date"><api:date><api:month>5</api:month><api:year>1999</api:year></api:date></api:field><api:field name="publication-status" type="text" display-name="Status"><api:text>Published</api:text></api:field><api:field name="record-created-at-source-date" type="date" display-name="Record created at source"><api:date><api:day>21</api:day><api:month>7</api:month><api:year>1999</api:year></api:date></api:field><api:field name="title" type="text" display-name="Title"><api:text>Plasticity in the mesenteric afferent response to cisplatin following vagotomy in the rat.</api:text></api:field><api:field name="types" type="list" display-name="Sub types"><api:items><api:item>Research Support, Non-U.S. Gov't</api:item><api:item>Journal Article</api:item></api:items></api:field><api:field name="volume" type="text" display-name="Volume"><api:text>76</api:text></api:field></api:native></api:record><api:record format="native" id="2908293" source-id="10" source-name="dimensions" source-display-name="Dimensions" id-at-source="pub.1026912352" last-modified-when="2024-03-31T08:41:53.097+01:00"><api:citation-count>26</api:citation-count><api:native><api:field name="authors" type="person-list" display-name="Authors"><api:people><api:person><api:last-name>Hillsley</api:last-name><api:initials>K</api:initials><api:first-names>K</api:first-names><api:separate-first-names><api:first-name>K</api:first-name></api:separate-first-names><api:addresses><api:address iso-country-code="GB"><api:line type="organisation">University of Sheffield</api:line><api:line type="city">Sheffield</api:line><api:line type="country">United Kingdom</api:line></api:address></api:addresses><api:identifiers><api:identifier scheme="dimensions-researcher-id">ur.01326661127.43</api:identifier></api:identifiers></api:person><api:person><api:links><api:link type="elements/user" id="2035" href="https://mypublications.shef.ac.uk:8091/secure-api/v6.13/users/2035"/></api:links><api:last-name>Grundy</api:last-name><api:initials>D</api:initials><api:first-names>D</api:first-names><api:separate-first-names><api:first-name>D</api:first-name></api:separate-first-names><api:addresses><api:address iso-country-code="GB"><api:line type="organisation">University of Sheffield</api:line><api:line type="city">Sheffield</api:line><api:line type="country">United Kingdom</api:line></api:address></api:addresses><api:identifiers><api:identifier scheme="dimensions-researcher-id">ur.01051044215.58</api:identifier></api:identifiers><api:author-types><api:author-type>corresponding</api:author-type></api:author-types></api:person></api:people></api:field><api:field name="doi" type="text" display-name="DOI"><api:text>10.1016/s0165-1838(99)00016-8</api:text><api:links><api:link type="doi" href="http://doi.org/10.1016/s0165-1838(99)00016-8"/><api:link type="altmetric" href="http://www.altmetric.com/details.php?doi=10.1016/s0165-1838(99)00016-8"/></api:links></api:field><api:field name="external-identifiers" type="identifier-list" display-name="External identifiers"><api:identifiers><api:identifier scheme="pubmed">10412832</api:identifier></api:identifiers></api:field><api:field name="issn" type="text" display-name="ISSN"><api:text>1566-0702</api:text><api:links><api:link type="elements/journal" href="https://mypublications.shef.ac.uk:8091/secure-api/v6.13/journals/972833"/></api:links></api:field><api:field name="issue" type="text" display-name="Issue"><api:text>2-3</api:text></api:field><api:field name="journal" type="text" display-name="Journal"><api:text>Autonomic Neuroscience</api:text></api:field><api:field name="keywords" type="keyword-list" display-name="Keywords"><api:keywords><api:keyword scheme="for-2020">32 Biomedical and Clinical Sciences</api:keyword><api:keyword scheme="for-2020">3209 Neurosciences</api:keyword><api:keyword scheme="rcdc">Neurosciences</api:keyword><api:keyword scheme="hrcs-rac">1.1 Normal biological development and functioning</api:keyword><api:keyword scheme="hrcs-rac">1 Underpinning research</api:keyword><api:keyword scheme="mesh">Animals</api:keyword><api:keyword scheme="mesh">Cisplatin</api:keyword><api:keyword scheme="mesh">Electric Stimulation</api:keyword><api:keyword scheme="mesh">Granisetron</api:keyword><api:keyword scheme="mesh">Jejunum</api:keyword><api:keyword scheme="mesh">Male</api:keyword><api:keyword scheme="mesh">Mesentery</api:keyword><api:keyword scheme="mesh">Neuronal Plasticity</api:keyword><api:keyword scheme="mesh">Neurons, Afferent</api:keyword><api:keyword scheme="mesh">Rats</api:keyword><api:keyword scheme="mesh">Rats, Wistar</api:keyword><api:keyword scheme="mesh">Serotonin</api:keyword><api:keyword scheme="mesh">Serotonin Antagonists</api:keyword><api:keyword scheme="mesh">Vagotomy</api:keyword></api:keywords></api:field><api:field name="open-access-status" type="text" display-name="Open access status"><api:text>Closed Access</api:text></api:field><api:field name="pagination" type="pagination" display-name="Pagination"><api:pagination><api:begin-page>93</api:begin-page><api:end-page>98</api:end-page></api:pagination></api:field><api:field name="publication-date" type="date" display-name="Publication date"><api:date><api:month>5</api:month><api:year>1999</api:year></api:date></api:field><api:field name="publisher" type="text" display-name="Publisher"><api:text>Elsevier</api:text></api:field><api:field name="record-created-at-source-date" type="date" display-name="Record created at source"><api:date><api:day>31</api:day><api:month>8</api:month><api:year>2017</api:year></api:date></api:field><api:field name="relative-citation-ratio" type="decimal" display-name="Relative citation ratio"><api:decimal>0.56</api:decimal></api:field><api:field name="title" type="text" display-name="Title"><api:text>Plasticity in the mesenteric afferent response to cisplatin following vagotomy in the rat</api:text></api:field><api:field name="volume" type="text" display-name="Volume"><api:text>76</api:text></api:field></api:native></api:record><api:record format="native" id="240225" source-id="11" source-name="wos-lite" source-display-name="Web of Science (Lite)" id-at-source="WOS:000080934200003" last-modified-when="2024-03-14T05:52:32.18+00:00"><api:citation-count>23</api:citation-count><api:native><api:field name="authors" type="person-list" display-name="Authors"><api:people><api:person><api:last-name>Hillsley</api:last-name><api:initials>K</api:initials><api:first-names>K</api:first-names><api:separate-first-names><api:first-name>K</api:first-name></api:separate-first-names></api:person><api:person><api:links><api:link type="elements/user" id="2035" href="https://mypublications.shef.ac.uk:8091/secure-api/v6.13/users/2035"/></api:links><api:last-name>Grundy</api:last-name><api:initials>D</api:initials><api:first-names>D</api:first-names><api:separate-first-names><api:first-name>D</api:first-name></api:separate-first-names></api:person></api:people></api:field><api:field name="author-url" type="text" display-name="Link 1"><api:text>https://www.webofscience.com/api/gateway?GWVersion=2&amp;SrcApp=sheffield_elements_live&amp;SrcAuth=WosAPI&amp;KeyUT=WOS:000080934200003&amp;DestLinkType=FullRecord&amp;DestApp=WOS_CPL</api:text></api:field><api:field name="doi" type="text" display-name="DOI"><api:text>10.1016/S0165-1838(99)00016-8</api:text><api:links><api:link type="doi" href="http://doi.org/10.1016/S0165-1838(99)00016-8"/><api:link type="altmetric" href="http://www.altmetric.com/details.php?doi=10.1016/S0165-1838(99)00016-8"/></api:links></api:field><api:field name="external-identifiers" type="identifier-list" display-name="External identifiers"><api:identifiers><api:identifier scheme="isidoc">207JR</api:identifier><api:identifier scheme="pubmed">10412832</api:identifier></api:identifiers></api:field><api:field name="issn" type="text" display-name="ISSN"><api:text>0165-1838</api:text><api:links><api:link type="elements/journal" href="https://mypublications.shef.ac.uk:8091/secure-api/v6.13/journals/984697"/></api:links></api:field><api:field name="issue" type="text" display-name="Issue"><api:text>2-3</api:text></api:field><api:field name="journal" type="text" display-name="Journal"><api:text>JOURNAL OF THE AUTONOMIC NERVOUS SYSTEM</api:text></api:field><api:field name="keywords" type="keyword-list" display-name="Keywords"><api:keywords><api:keyword>emesis</api:keyword><api:keyword>serotonin</api:keyword><api:keyword>vagus nerve</api:keyword><api:keyword>small intestine</api:keyword></api:keywords></api:field><api:field name="pagination" type="pagination" display-name="Pagination"><api:pagination><api:begin-page>93</api:begin-page><api:end-page>98</api:end-page></api:pagination></api:field><api:field name="publication-date" type="date" display-name="Publication date"><api:date><api:year>1999</api:year></api:date></api:field><api:field name="publication-status" type="text" display-name="Status"><api:text>Published</api:text></api:field><api:field name="title" type="text" display-name="Title"><api:text>Plasticity in the mesenteric afferent response to cisplatin following vagotomy in the rat</api:text></api:field><api:field name="types" type="list" display-name="Sub types"><api:items><api:item>Article</api:item></api:items></api:field><api:field name="volume" type="text" display-name="Volume"><api:text>76</api:text></api:field></api:native></api:record><api:record format="native" id="22855" source-id="3" source-name="wos" source-display-name="Web of Science" id-at-source="WOS:000080934200003" last-modified-when="2014-07-25T11:02:45.637+01:00"><api:citation-count>15</api:citation-count><api:native><api:field name="authors" type="person-list" display-name="Authors"><api:people><api:person><api:last-name>Hillsley</api:last-name><api:initials>K</api:initials><api:first-names>K</api:first-names><api:separate-first-names><api:first-name>K</api:first-name></api:separate-first-names></api:person><api:person><api:links><api:link type="elements/user" id="2035" href="https://mypublications.shef.ac.uk:8091/secure-api/v6.13/users/2035"/></api:links><api:last-name>Grundy</api:last-name><api:initials>D</api:initials><api:first-names>D</api:first-names><api:separate-first-names><api:first-name>D</api:first-name></api:separate-first-names></api:person></api:people></api:field><api:field name="issn" type="text" display-name="ISSN"><api:text>0165-1838</api:text><api:links><api:link type="elements/journal" href="https://mypublications.shef.ac.uk:8091/secure-api/v6.13/journals/984697"/></api:links></api:field><api:field name="issue" type="text" display-name="Issue"><api:text>2-3</api:text></api:field><api:field name="journal" type="text" display-name="Journal"><api:text>J AUTONOM NERV SYST</api:text></api:field><api:field name="keywords" type="keyword-list" display-name="Keywords"><api:keywords><api:keyword>emesis</api:keyword><api:keyword>serotonin</api:keyword><api:keyword>vagus nerve</api:keyword><api:keyword>small intestine</api:keyword><api:keyword>GASTROINTESTINAL-TRACT</api:keyword><api:keyword>SEROTONIN METABOLISM</api:keyword><api:keyword>SMALL-INTESTINE</api:keyword><api:keyword>EMESIS</api:keyword><api:keyword>FERRET</api:keyword><api:keyword>FIBERS</api:keyword><api:keyword>5-HYDROXYTRYPTAMINE</api:keyword><api:keyword>DEXAMETHASONE</api:keyword><api:keyword>RECEPTORS</api:keyword><api:keyword>PLATINUM</api:keyword></api:keywords></api:field><api:field name="pagination" type="pagination" display-name="Pagination"><api:pagination><api:begin-page>93</api:begin-page><api:end-page>98</api:end-page></api:pagination></api:field><api:field name="publication-date" type="date" display-name="Publication date"><api:date><api:day>28</api:day><api:month>5</api:month><api:year>1999</api:year></api:date></api:field><api:field name="title" type="text" display-name="Title"><api:text>Plasticity in the mesenteric afferent response to cisplatin following vagotomy in the rat</api:text></api:field><api:field name="volume" type="text" display-name="Volume"><api:text>76</api:text></api:field></api:native></api:record></api:records><api:fields/><api:all-labels type="keyword-list"><api:keywords><api:keyword scheme="mesh" origin="record-data" source="pubmed">Animals</api:keyword><api:keyword scheme="mesh" origin="record-data" source="pubmed">Cisplatin</api:keyword><api:keyword scheme="mesh" origin="record-data" source="pubmed">Electric Stimulation</api:keyword><api:keyword scheme="mesh" origin="record-data" source="pubmed">Granisetron</api:keyword><api:keyword scheme="mesh" origin="record-data" source="pubmed">Jejunum</api:keyword><api:keyword scheme="mesh" origin="record-data" source="pubmed">Male</api:keyword><api:keyword scheme="mesh" origin="record-data" source="pubmed">Mesentery</api:keyword><api:keyword scheme="mesh" origin="record-data" source="pubmed">Neuronal Plasticity</api:keyword><api:keyword scheme="mesh" origin="record-data" source="pubmed">Neurons, Afferent</api:keyword><api:keyword scheme="mesh" origin="record-data" source="pubmed">Rats</api:keyword><api:keyword scheme="mesh" origin="record-data" source="pubmed">Rats, Wistar</api:keyword><api:keyword scheme="mesh" origin="record-data" source="pubmed">Serotonin</api:keyword><api:keyword scheme="mesh" origin="record-data" source="pubmed">Serotonin Antagonists</api:keyword><api:keyword scheme="mesh" origin="record-data" source="pubmed">Vagotomy</api:keyword><api:keyword scheme="mesh" origin="record-data" source="epmc">Mesentery</api:keyword><api:keyword scheme="mesh" origin="record-data" source="epmc">Jejunum</api:keyword><api:keyword scheme="mesh" origin="record-data" source="epmc">Neurons, Afferent</api:keyword><api:keyword scheme="mesh" origin="record-data" source="epmc">Animals</api:keyword><api:keyword scheme="mesh" origin="record-data" source="epmc">Rats</api:keyword><api:keyword scheme="mesh" origin="record-data" source="epmc">Rats, Wistar</api:keyword><api:keyword scheme="mesh" origin="record-data" source="epmc">Cisplatin</api:keyword><api:keyword scheme="mesh" origin="record-data" source="epmc">Serotonin</api:keyword><api:keyword scheme="mesh" origin="record-data" source="epmc">Granisetron</api:keyword><api:keyword scheme="mesh" origin="record-data" source="epmc">Serotonin Antagonists</api:keyword><api:keyword scheme="mesh" origin="record-data" source="epmc">Vagotomy</api:keyword><api:keyword scheme="mesh" origin="record-data" source="epmc">Electric Stimulation</api:keyword><api:keyword scheme="mesh" origin="record-data" source="epmc">Neuronal Plasticity</api:keyword><api:keyword scheme="mesh" origin="record-data" source="epmc">Male</api:keyword><api:keyword scheme="for-2020" origin="record-data" source="dimensions">32 Biomedical and Clinical Sciences</api:keyword><api:keyword scheme="for-2020" origin="record-data" source="dimensions">3209 Neurosciences</api:keyword><api:keyword scheme="rcdc" origin="record-data" source="dimensions">Neurosciences</api:keyword><api:keyword scheme="hrcs-rac" origin="record-data" source="dimensions">1.1 Normal biological development and functioning</api:keyword><api:keyword scheme="hrcs-rac" origin="record-data" source="dimensions">1 Underpinning research</api:keyword><api:keyword scheme="mesh" origin="record-data" source="dimensions">Animals</api:keyword><api:keyword scheme="mesh" origin="record-data" source="dimensions">Cisplatin</api:keyword><api:keyword scheme="mesh" origin="record-data" source="dimensions">Electric Stimulation</api:keyword><api:keyword scheme="mesh" origin="record-data" source="dimensions">Granisetron</api:keyword><api:keyword scheme="mesh" origin="record-data" source="dimensions">Jejunum</api:keyword><api:keyword scheme="mesh" origin="record-data" source="dimensions">Male</api:keyword><api:keyword scheme="mesh" origin="record-data" source="dimensions">Mesentery</api:keyword><api:keyword scheme="mesh" origin="record-data" source="dimensions">Neuronal Plasticity</api:keyword><api:keyword scheme="mesh" origin="record-data" source="dimensions">Neurons, Afferent</api:keyword><api:keyword scheme="mesh" origin="record-data" source="dimensions">Rats</api:keyword><api:keyword scheme="mesh" origin="record-data" source="dimensions">Rats, Wistar</api:keyword><api:keyword scheme="mesh" origin="record-data" source="dimensions">Serotonin</api:keyword><api:keyword scheme="mesh" origin="record-data" source="dimensions">Serotonin Antagonists</api:keyword><api:keyword scheme="mesh" origin="record-data" source="dimensions">Vagotomy</api:keyword><api:keyword origin="record-data" source="wos-lite">emesis</api:keyword><api:keyword origin="record-data" source="wos-lite">serotonin</api:keyword><api:keyword origin="record-data" source="wos-lite">vagus nerve</api:keyword><api:keyword origin="record-data" source="wos-lite">small intestine</api:keyword><api:keyword origin="record-data" source="wos">emesis</api:keyword><api:keyword origin="record-data" source="wos">serotonin</api:keyword><api:keyword origin="record-data" source="wos">vagus nerve</api:keyword><api:keyword origin="record-data" source="wos">small intestine</api:keyword><api:keyword origin="record-data" source="wos">GASTROINTESTINAL-TRACT</api:keyword><api:keyword origin="record-data" source="wos">SEROTONIN METABOLISM</api:keyword><api:keyword origin="record-data" source="wos">SMALL-INTESTINE</api:keyword><api:keyword origin="record-data" source="wos">EMESIS</api:keyword><api:keyword origin="record-data" source="wos">FERRET</api:keyword><api:keyword origin="record-data" source="wos">FIBERS</api:keyword><api:keyword origin="record-data" source="wos">5-HYDROXYTRYPTAMINE</api:keyword><api:keyword origin="record-data" source="wos">DEXAMETHASONE</api:keyword><api:keyword origin="record-data" source="wos">RECEPTORS</api:keyword><api:keyword origin="record-data" source="wos">PLATINUM</api:keyword><api:keyword scheme="science-metrix" origin="issn-inferred">Neurology &amp; Neurosurgery</api:keyword></api:keywords></api:all-labels><api:journal issn="0165-1838" href="https://mypublications.shef.ac.uk:8091/secure-api/v6.13/journals/984697" title="Journal of the autonomic nervous system"><api:records><api:record source-name="summary"><api:title>Journal of the autonomic nervous system</api:title></api:record></api:records></api:journal><api:relationships href="https://mypublications.shef.ac.uk:8091/secure-api/v6.13/publications/373/relationships"/></api:object></api:result></api:response>